{
	"name": "Hydra",
	"descriptionmsg": "hydra-skin-desc",
	"namemsg": "skinname-hydra",
	"license-name": "GPL-2.0+",
	"type": "skin",
	"ConfigRegistry": {
		"hydraskin": "GlobalVarConfig::newInstance"
	},
	"config": {
		"HydraSkinUseDark": false
	},
	"MessagesDirs": {
		"Hydra": [
			"i18n"
		]
	},
	"ResourceModules": {
		"skins.hydra.styles": {
			"position": "top",
			"styles": {
				"css/hydra.css": {
					"media": "screen"
				}
			}
		},
		"skins.hydra.footer": {
			"styles": {
				"css/footer.css": {
					"media": "screen"
				}
			},
			"position": "top"
		},
		"skins.hydra.netbar": {
			"styles": {
				"css/netbar.css": {
					"media": "screen"
				}
			},
			"position": "top"
		}
	},
	"ResourceFileModulePaths": {
		"localBasePath": "",
		"remoteSkinPath": "Hydra"
	},
	"AutoloadClasses": {
		"HydraTemplate": "HydraTemplate.php",
		"HydraHooks": "HydraHooks.php"
	},
	"Hooks": {
		"SkinPreloadExistence": [
			"HydraHooks::onSkinPreloadExistence"
		],
		"SkinTemplateOutputPageBeforeExec": [
			"HydraHooks::onSkinTemplateOutputPageBeforeExec"
		],
		"OutputPageBodyAttributes": [
			"HydraHooks::onOutputPageBodyAttributes"
		],
		"SkinVectorStyleModules": [
			"HydraHooks::onSkinVectorStyleModules"
		]
	},
	"manifest_version": 1
}
